amqpdispatcher/__init__.py
amqpdispatcher/amqp_proxy.py
amqpdispatcher/channel_proxy.py
amqpdispatcher/connection_proxy.py
amqpdispatcher/consumer_pool.py
amqpdispatcher/dispatcher.py
amqpdispatcher/dispatcher_common.py
amqpdispatcher/dispatcher_haigha.py
amqpdispatcher/dispatcher_pika.py
amqpdispatcher/message.py
amqpdispatcher/validate.py
amqp_dispatcher-0.11.0.dist-info/METADATA
amqp_dispatcher-0.11.0.dist-info/WHEEL
amqp_dispatcher-0.11.0.dist-info/entry_points.txt
amqp_dispatcher-0.11.0.dist-info/top_level.txt
amqp_dispatcher-0.11.0.dist-info/zip-safe
amqp_dispatcher-0.11.0.dist-info/RECORD
