Metadata-Version: 2.1
Name: amqp-dispatcher
Version: 0.11.0
Summary: A daemon gevent to run AMQP consumers
Home-page: http://github.com/opschops/amqp-dispatcher
Author: Jose Diaz-Gonzalez
Author-email: opschops@josediazgonzalez.com
License: BSD
Keywords: amqp
Platform: UNKNOWN
Requires-Dist: gevent
Requires-Dist: haigha
Requires-Dist: pyyaml
Requires-Dist: pika
